nandboxbots/NandboxClient.py
nandboxbots/__init__.py
nandboxbots/nandbox.py
nandboxbots/data/Article.py
nandboxbots/data/Audio.py
nandboxbots/data/Button.py
nandboxbots/data/ButtonQueryResult.py
nandboxbots/data/Category.py
nandboxbots/data/Chat.py
nandboxbots/data/CollectionProduct.py
nandboxbots/data/Contact.py
nandboxbots/data/Data.py
nandboxbots/data/Document.py
nandboxbots/data/Gif.py
nandboxbots/data/Image.py
nandboxbots/data/Location.py
nandboxbots/data/Menu.py
nandboxbots/data/Photo.py
nandboxbots/data/ProductItem.py
nandboxbots/data/Result.py
nandboxbots/data/Row.py
nandboxbots/data/SignupUser.py
nandboxbots/data/Sticker.py
nandboxbots/data/TagDefinition.py
nandboxbots/data/TextFile.py
nandboxbots/data/Thumbnail.py
nandboxbots/data/User.py
nandboxbots/data/Video.py
nandboxbots/data/Voice.py
nandboxbots/data/WhiteListUser.py
nandboxbots/data/WorkflowCell.py
nandboxbots/data/__init__.py
nandboxbots/inmessages/BlackList.py
nandboxbots/inmessages/ChatAdministrators.py
nandboxbots/inmessages/ChatMember.py
nandboxbots/inmessages/ChatMenuCallback.py
nandboxbots/inmessages/GetCollectionProductResponse.py
nandboxbots/inmessages/GetProductItemResponse.py
nandboxbots/inmessages/IncomingMessage.py
nandboxbots/inmessages/InlineMessageCallback.py
nandboxbots/inmessages/InlineSearch.py
nandboxbots/inmessages/ListCollectionItemResponse.py
nandboxbots/inmessages/MessageAck.py
nandboxbots/inmessages/Pattern.py
nandboxbots/inmessages/PermanentUrl.py
nandboxbots/inmessages/WhiteList.py
nandboxbots/inmessages/WhiteList_ak.py
nandboxbots/inmessages/WorkflowDetails.py
nandboxbots/inmessages/__init__.py
nandboxbots/outmessages/AddBlackListOutMessage.py
nandboxbots/outmessages/AddBlacklistPatternsOutMessage.py
nandboxbots/outmessages/AddChatAdminMemberOutMessage.py
nandboxbots/outmessages/AddChatMemberOutMessage.py
nandboxbots/outmessages/AddWhiteListOutMessage.py
nandboxbots/outmessages/AddWhitelistPatternsOutMessage.py
nandboxbots/outmessages/ArticleOutMessage.py
nandboxbotsapi-1.5.3.dist-info/METADATA
nandboxbotsapi-1.5.3.dist-info/WHEEL
nandboxbotsapi-1.5.3.dist-info/entry_points.txt
nandboxbotsapi-1.5.3.dist-info/top_level.txt
nandboxbotsapi-1.5.3.dist-info/RECORD
