Metadata-Version: 2.1
Name: nandboxbotsapi
Version: 1.5.3
Summary: A Python library to interact with official nandbox Bot API.
Home-page: 
Author: Amir Salah
Author-email: ameer.alahmedy@nandbox.com
Project-URL: Bug Reports, https://github.com/nandbox/nandboxbotsapi-py/issues
Project-URL: Source, https://github.com/nandbox/nandboxbotsapi-py
Keywords: nandbox,bot,api
Classifier: Development Status :: 3 - Alpha
Classifier: Intended Audience :: Developers
Classifier: Topic :: Software Development :: Libraries :: Application Frameworks
Classifier: License :: OSI Approved :: MIT License
Classifier: Programming Language :: Python :: 3.9
Classifier: Programming Language :: Python :: 3.10
Classifier: Programming Language :: Python :: 3 :: Only
Requires-Python: >=3.9, <4
Requires-Dist: requests==2.26.0
Requires-Dist: websocket-client==1.2.1
Requires-Dist: websockets==10.0
